laz3/__init__.py
laz3/laz3.py
laz3-0.0.6.dist-info/LICENSE
laz3-0.0.6.dist-info/METADATA
laz3-0.0.6.dist-info/WHEEL
laz3-0.0.6.dist-info/top_level.txt
laz3-0.0.6.dist-info/RECORD
