Metadata-Version: 2.1
Name: laz3
Version: 0.0.6
Summary: A encoding algorithm using a password
Home-page: https://github.com/KuriWasTaken/laz3/tree/main
Author: Kuri
Author-email: author@example.com
License: UNKNOWN
Project-URL: Bug Tracker, https://github.com/KuriWasTaken/laz3/issues
Platform: UNKNOWN
Classifier: Programming Language :: Python :: 3
Classifier: License :: OSI Approved :: MIT License
Classifier: Operating System :: OS Independent
Requires-Python: >=3.6
License-File: LICENSE
